{
    "id": "12",
    "boundaries": [
      {
        "latitude": 8.933021666666667,
        "longitude": -79.54669666666666
      },
      {
        "latitude": 8.936243333333334,
        "longitude": -79.54532333333333
      },
      {
        "latitude": 8.939805,
        "longitude": -79.54532333333333
      },
      {
        "latitude": 8.94167,
        "longitude": -79.54995666666667
      },
      {
        "latitude": 8.943026666666666,
        "longitude": -79.55321833333333
      },
      {
        "latitude": 8.946248333333333,
        "longitude": -79.554935
      },
      {
        "latitude": 8.947435,
        "longitude": -79.55253166666667
      },
      {
        "latitude": 8.946078333333332,
        "longitude": -79.54927166666667
      },
      {
        "latitude": 8.947435,
        "longitude": -79.54601
      },
      {
        "latitude": 8.948791666666667,
        "longitude": -79.54292
      },
      {
        "latitude": 8.948961666666667,
        "longitude": -79.54017333333333
      },
      {
        "latitude": 8.950656666666667,
        "longitude": -79.53862833333334
      },
      {
        "latitude": 8.951505,
        "longitude": -79.53588166666667
      },
      {
        "latitude": 8.951843333333333,
        "longitude": -79.53382166666667
      },
      {
        "latitude": 8.952691666666666,
        "longitude": -79.53382166666667
      },
      {
        "latitude": 8.953031666666666,
        "longitude": -79.53656833333334
      },
      {
        "latitude": 8.955235,
        "longitude": -79.537255
      },
      {
        "latitude": 8.959135,
        "longitude": -79.53742666666666
      },
      {
        "latitude": 8.962526666666667,
        "longitude": -79.536225
      },
      {
        "latitude": 8.968631666666667,
        "longitude": -79.53244833333333
      },
      {
        "latitude": 8.970666666666666,
        "longitude": -79.53038833333333
      },
      {
        "latitude": 8.973378333333333,
        "longitude": -79.52764166666667
      },
      {
        "latitude": 8.975243333333333,
        "longitude": -79.52626833333333
      },
      {
        "latitude": 8.975921666666666,
        "longitude": -79.523865
      },
      {
        "latitude": 8.975921666666666,
        "longitude": -79.51991666666666
      },
      {
        "latitude": 8.975921666666666,
        "longitude": -79.51699833333333
      },
      {
        "latitude": 8.974056666666666,
        "longitude": -79.51631166666667
      },
      {
        "latitude": 8.972361666666666,
        "longitude": -79.51648333333333
      },
      {
        "latitude": 8.972191666666667,
        "longitude": -79.51528166666667
      },
      {
        "latitude": 8.974735,
        "longitude": -79.51339333333334
      },
      {
        "latitude": 8.976091666666667,
        "longitude": -79.51116166666667
      },
      {
        "latitude": 8.976261666666666,
        "longitude": -79.50875833333333
      },
      {
        "latitude": 8.975753333333333,
        "longitude": -79.50755666666667
      },
      {
        "latitude": 8.97677,
        "longitude": -79.50669833333333
      },
      {
        "latitude": 8.978805,
        "longitude": -79.507385
      },
      {
        "latitude": 8.982026666666666,
        "longitude": -79.507385
      },
      {
        "latitude": 8.983891666666667,
        "longitude": -79.50618333333334
      },
      {
        "latitude": 8.98457,
        "longitude": -79.504295
      },
      {
        "latitude": 8.986943333333333,
        "longitude": -79.50275
      },
      {
        "latitude": 8.989995,
        "longitude": -79.49948833333333
      },
      {
        "latitude": 8.991521666666667,
        "longitude": -79.49794333333334
      },
      {
        "latitude": 8.992708333333333,
        "longitude": -79.4976
      },
      {
        "latitude": 8.995421666666667,
        "longitude": -79.49725666666667
      },
      {
        "latitude": 8.99593,
        "longitude": -79.49639833333333
      },
      {
        "latitude": 8.997286666666668,
        "longitude": -79.49622666666667
      },
      {
        "latitude": 8.99983,
        "longitude": -79.497085
      },
      {
        "latitude": 9.00339,
        "longitude": -79.497085
      },
      {
        "latitude": 9.006103333333334,
        "longitude": -79.49416833333333
      },
      {
        "latitude": 9.00729,
        "longitude": -79.48987666666666
      },
      {
        "latitude": 9.00729,
        "longitude": -79.48730166666667
      },
      {
        "latitude": 9.00729,
        "longitude": -79.48575666666666
      },
      {
        "latitude": 9.00695,
        "longitude": -79.48472666666666
      },
      {
        "latitude": 9.008136666666667,
        "longitude": -79.48335333333333
      },
      {
        "latitude": 9.009663333333334,
        "longitude": -79.48283833333333
      },
      {
        "latitude": 9.010001666666666,
        "longitude": -79.48163666666666
      },
      {
        "latitude": 9.009323333333333,
        "longitude": -79.48026333333334
      },
      {
        "latitude": 9.008645,
        "longitude": -79.47889
      },
      {
        "latitude": 9.008645,
        "longitude": -79.477345
      },
      {
        "latitude": 9.008985,
        "longitude": -79.475285
      },
      {
        "latitude": 9.009493333333333,
        "longitude": -79.47356833333333
      },
      {
        "latitude": 9.010171666666666,
        "longitude": -79.47202333333334
      },
      {
        "latitude": 9.01085,
        "longitude": -79.46996333333334
      },
      {
        "latitude": 9.01085,
        "longitude": -79.46859
      },
      {
        "latitude": 9.01085,
        "longitude": -79.46670166666667
      },
      {
        "latitude": 9.010171666666666,
        "longitude": -79.46515666666667
      },
      {
        "latitude": 9.008645,
        "longitude": -79.46429833333333
      },
      {
        "latitude": 9.008645,
        "longitude": -79.46241
      },
      {
        "latitude": 9.008815,
        "longitude": -79.46000666666667
      },
      {
        "latitude": 9.01085,
        "longitude": -79.45794666666667
      },
      {
        "latitude": 9.012375,
        "longitude": -79.45726
      },
      {
        "latitude": 9.012885,
        "longitude": -79.45451333333334
      },
      {
        "latitude": 9.012206666666666,
        "longitude": -79.45228166666666
      },
      {
        "latitude": 9.011528333333333,
        "longitude": -79.45073666666667
      },
      {
        "latitude": 9.011528333333333,
        "longitude": -79.448505
      },
      {
        "latitude": 9.012036666666667,
        "longitude": -79.445415
      },
      {
        "latitude": 9.013393333333333,
        "longitude": -79.44198166666666
      },
      {
        "latitude": 9.015426666666666,
        "longitude": -79.44078166666667
      },
      {
        "latitude": 9.017461666666666,
        "longitude": -79.43889333333334
      },
      {
        "latitude": 9.020005,
        "longitude": -79.43683333333334
      },
      {
        "latitude": 9.018648333333333,
        "longitude": -79.43460166666667
      },
      {
        "latitude": 9.016105,
        "longitude": -79.43271333333334
      },
      {
        "latitude": 9.01475,
        "longitude": -79.4334
      },
      {
        "latitude": 9.01424,
        "longitude": -79.42893666666667
      },
      {
        "latitude": 9.01424,
        "longitude": -79.42498833333333
      },
      {
        "latitude": 9.015088333333333,
        "longitude": -79.420525
      },
      {
        "latitude": 9.015766666666666,
        "longitude": -79.41571833333333
      },
      {
        "latitude": 9.016445,
        "longitude": -79.41245666666667
      },
      {
        "latitude": 9.017631666666666,
        "longitude": -79.40953833333333
      },
      {
        "latitude": 9.018818333333334,
        "longitude": -79.40765
      },
      {
        "latitude": 9.0217,
        "longitude": -79.40747833333333
      },
      {
        "latitude": 9.019496666666667,
        "longitude": -79.40215666666667
      },
      {
        "latitude": 9.025938333333333,
        "longitude": -79.39923833333333
      },
      {
        "latitude": 9.019835,
        "longitude": -79.39151333333334
      },
      {
        "latitude": 9.020343333333333,
        "longitude": -79.38396166666666
      },
      {
        "latitude": 9.020853333333333,
        "longitude": -79.37846833333333
      },
      {
        "latitude": 9.021191666666667,
        "longitude": -79.37228833333333
      },
      {
        "latitude": 9.02153,
        "longitude": -79.36610833333333
      },
      {
        "latitude": 9.022378333333334,
        "longitude": -79.36130166666666
      },
      {
        "latitude": 9.022378333333334,
        "longitude": -79.358555
      },
      {
        "latitude": 9.026616666666667,
        "longitude": -79.35701
      },
      {
        "latitude": 9.027803333333333,
        "longitude": -79.35512166666666
      },
      {
        "latitude": 9.028481666666666,
        "longitude": -79.35220333333334
      },
      {
        "latitude": 9.027125,
        "longitude": -79.348255
      },
      {
        "latitude": 9.024413333333333,
        "longitude": -79.34739666666667
      },
      {
        "latitude": 9.024581666666666,
        "longitude": -79.32885833333333
      },
      {
        "latitude": 9.024581666666666,
        "longitude": -79.32096166666666
      },
      {
        "latitude": 9.024581666666666,
        "longitude": -79.31426666666667
      },
      {
        "latitude": 9.024413333333333,
        "longitude": -79.30928833333333
      },
      {
        "latitude": 9.026616666666667,
        "longitude": -79.30465333333333
      },
      {
        "latitude": 9.027973333333334,
        "longitude": -79.30139166666666
      },
      {
        "latitude": 9.027465,
        "longitude": -79.29572666666667
      },
      {
        "latitude": 9.027125,
        "longitude": -79.28954666666667
      },
      {
        "latitude": 9.028651666666667,
        "longitude": -79.287315
      },
      {
        "latitude": 9.02882,
        "longitude": -79.28474
      },
      {
        "latitude": 9.026616666666667,
        "longitude": -79.28079166666667
      },
      {
        "latitude": 9.023735,
        "longitude": -79.272725
      },
      {
        "latitude": 9.023735,
        "longitude": -79.26929166666666
      },
      {
        "latitude": 9.023735,
        "longitude": -79.26517166666666
      },
      {
        "latitude": 9.023226666666666,
        "longitude": -79.26276833333333
      },
      {
        "latitude": 9.0217,
        "longitude": -79.25555833333334
      },
      {
        "latitude": 9.015596666666667,
        "longitude": -79.20921
      },
      {
        "latitude": 9.01424,
        "longitude": -79.18328833333334
      },
      {
        "latitude": 9.017291666666667,
        "longitude": -79.18019833333334
      },
      {
        "latitude": 9.017631666666666,
        "longitude": -79.17539166666667
      },
      {
        "latitude": 9.030855,
        "longitude": -79.17590666666666
      },
      {
        "latitude": 9.02882,
        "longitude": -79.17298833333334
      },
      {
        "latitude": 9.02153,
        "longitude": -79.171615
      },
      {
        "latitude": 9.016953333333333,
        "longitude": -79.16715333333333
      },
      {
        "latitude": 9.015258333333334,
        "longitude": -79.16578
      },
      {
        "latitude": 9.01475,
        "longitude": -79.15822666666666
      },
      {
        "latitude": 9.011528333333333,
        "longitude": -79.14346333333333
      },
      {
        "latitude": 9.009155,
        "longitude": -79.13419333333333
      },
      {
        "latitude": 9.004406666666666,
        "longitude": -79.12852833333334
      },
      {
        "latitude": 9.001525,
        "longitude": -79.125095
      },
      {
        "latitude": 9.00695,
        "longitude": -79.11308
      },
      {
        "latitude": 9.012545,
        "longitude": -79.10896
      },
      {
        "latitude": 9.021021666666666,
        "longitude": -79.10140666666666
      },
      {
        "latitude": 9.02882,
        "longitude": -79.09763
      },
      {
        "latitude": 9.03984,
        "longitude": -79.09522666666666
      },
      {
        "latitude": 9.050181666666667,
        "longitude": -79.09351
      },
      {
        "latitude": 9.05798,
        "longitude": -79.09162166666667
      },
      {
        "latitude": 9.06154,
        "longitude": -79.09076333333333
      },
      {
        "latitude": 9.066286666666667,
        "longitude": -79.09419666666666
      },
      {
        "latitude": 9.073575,
        "longitude": -79.09694333333333
      },
      {
        "latitude": 9.079678333333334,
        "longitude": -79.09986166666667
      },
      {
        "latitude": 9.083576666666668,
        "longitude": -79.10140666666666
      },
      {
        "latitude": 9.086458333333333,
        "longitude": -79.09780166666667
      },
      {
        "latitude": 9.071031666666666,
        "longitude": -79.08715833333333
      },
      {
        "latitude": 9.0612,
        "longitude": -79.08286666666666
      },
      {
        "latitude": 9.051198333333334,
        "longitude": -79.08424
      },
      {
        "latitude": 9.043908333333333,
        "longitude": -79.08647166666667
      },
      {
        "latitude": 9.031195,
        "longitude": -79.085785
      },
      {
        "latitude": 9.022378333333334,
        "longitude": -79.08904666666666
      },
      {
        "latitude": 9.014918333333334,
        "longitude": -79.09436833333334
      },
      {
        "latitude": 9.006441666666667,
        "longitude": -79.09385333333333
      },
      {
        "latitude": 9.001016666666667,
        "longitude": -79.099175
      },
      {
        "latitude": 8.996438333333334,
        "longitude": -79.10484
      },
      {
        "latitude": 8.993046666666666,
        "longitude": -79.10484
      },
      {
        "latitude": 8.990335,
        "longitude": -79.09848833333334
      },
      {
        "latitude": 8.989316666666667,
        "longitude": -79.09471166666667
      },
      {
        "latitude": 8.992538333333334,
        "longitude": -79.0863
      },
      {
        "latitude": 8.9922,
        "longitude": -79.07840333333333
      },
      {
        "latitude": 8.988638333333334,
        "longitude": -79.068275
      },
      {
        "latitude": 8.98474,
        "longitude": -79.06055166666667
      },
      {
        "latitude": 8.98084,
        "longitude": -79.04973666666666
      },
      {
        "latitude": 8.977448333333333,
        "longitude": -79.04596
      },
      {
        "latitude": 8.979821666666666,
        "longitude": -79.04321333333333
      },
      {
        "latitude": 8.982873333333334,
        "longitude": -79.04304166666667
      },
      {
        "latitude": 8.98423,
        "longitude": -79.03857833333333
      },
      {
        "latitude": 8.979991666666667,
        "longitude": -79.03051
      },
      {
        "latitude": 8.973378333333333,
        "longitude": -79.02776333333334
      },
      {
        "latitude": 8.969648333333334,
        "longitude": -79.02003833333333
      },
      {
        "latitude": 8.968461666666666,
        "longitude": -79.01111166666666
      },
      {
        "latitude": 8.962866666666667,
        "longitude": -78.99961166666667
      },
      {
        "latitude": 8.955405,
        "longitude": -78.984505
      },
      {
        "latitude": 8.946756666666667,
        "longitude": -78.97643666666667
      },
      {
        "latitude": 8.948113333333334,
        "longitude": -78.96922666666667
      },
      {
        "latitude": 8.944891666666667,
        "longitude": -78.96321833333333
      },
      {
        "latitude": 8.934886666666667,
        "longitude": -78.941075
      },
      {
        "latitude": 8.938616666666666,
        "longitude": -78.93987333333334
      },
      {
        "latitude": 8.938956666666666,
        "longitude": -78.93317833333333
      },
      {
        "latitude": 8.935225,
        "longitude": -78.9282
      },
      {
        "latitude": 8.92963,
        "longitude": -78.9282
      },
      {
        "latitude": 8.930816666666667,
        "longitude": -78.92287833333333
      },
      {
        "latitude": 8.929121666666667,
        "longitude": -78.915325
      },
      {
        "latitude": 8.925051666666667,
        "longitude": -78.90845833333333
      },
      {
        "latitude": 8.917758333333333,
        "longitude": -78.90519666666667
      },
      {
        "latitude": 8.913688333333333,
        "longitude": -78.907085
      },
      {
        "latitude": 8.909958333333334,
        "longitude": -78.90365166666666
      },
      {
        "latitude": 8.90877,
        "longitude": -78.89901833333333
      },
      {
        "latitude": 8.906566666666667,
        "longitude": -78.89678666666667
      },
      {
        "latitude": 8.904191666666666,
        "longitude": -78.89129333333334
      },
      {
        "latitude": 8.898595,
        "longitude": -78.887345
      },
      {
        "latitude": 8.895541666666666,
        "longitude": -78.88854666666667
      },
      {
        "latitude": 8.894525,
        "longitude": -78.88253833333333
      },
      {
        "latitude": 8.878243333333334,
        "longitude": -78.87841833333333
      },
      {
        "latitude": 8.873155,
        "longitude": -78.87584333333334
      },
      {
        "latitude": 8.869423333333334,
        "longitude": -78.87790333333334
      },
      {
        "latitude": 8.86637,
        "longitude": -78.87429833333333
      },
      {
        "latitude": 8.864165,
        "longitude": -78.87515666666667
      },
      {
        "latitude": 8.852801666666666,
        "longitude": -78.87206666666667
      },
      {
        "latitude": 8.841606666666667,
        "longitude": -78.86691666666667
      },
      {
        "latitude": 8.840928333333334,
        "longitude": -78.8652
      },
      {
        "latitude": 8.829563333333333,
        "longitude": -78.86005
      },
      {
        "latitude": 8.831428333333333,
        "longitude": -78.85799
      },
      {
        "latitude": 8.825491666666666,
        "longitude": -78.85318333333333
      },
      {
        "latitude": 8.820063333333334,
        "longitude": -78.84786166666666
      },
      {
        "latitude": 8.814635,
        "longitude": -78.83893666666667
      },
      {
        "latitude": 8.814635,
        "longitude": -78.83550333333334
      },
      {
        "latitude": 8.817858333333334,
        "longitude": -78.83292833333333
      },
      {
        "latitude": 8.821421666666666,
        "longitude": -78.83018166666666
      },
      {
        "latitude": 8.825323333333333,
        "longitude": -78.82812166666666
      },
      {
        "latitude": 8.830071666666667,
        "longitude": -78.82520333333333
      },
      {
        "latitude": 8.833465,
        "longitude": -78.82194166666666
      },
      {
        "latitude": 8.83533,
        "longitude": -78.81644833333333
      },
      {
        "latitude": 8.83567,
        "longitude": -78.81061166666667
      },
      {
        "latitude": 8.837705,
        "longitude": -78.804775
      },
      {
        "latitude": 8.837705,
        "longitude": -78.80134166666667
      },
      {
        "latitude": 8.837026666666667,
        "longitude": -78.79911
      },
      {
        "latitude": 8.842455,
        "longitude": -78.80134166666667
      },
      {
        "latitude": 8.845508333333333,
        "longitude": -78.80185666666667
      },
      {
        "latitude": 8.850935,
        "longitude": -78.80254333333333
      },
      {
        "latitude": 8.855006666666666,
        "longitude": -78.800655
      },
      {
        "latitude": 8.856871666666667,
        "longitude": -78.795505
      },
      {
        "latitude": 8.850088333333334,
        "longitude": -78.79430333333333
      },
      {
        "latitude": 8.856193333333334,
        "longitude": -78.79138666666667
      },
      {
        "latitude": 8.852631666666667,
        "longitude": -78.78692333333333
      },
      {
        "latitude": 8.848391666666666,
        "longitude": -78.77919833333333
      },
      {
        "latitude": 8.843471666666666,
        "longitude": -78.77610833333334
      },
      {
        "latitude": 8.838383333333333,
        "longitude": -78.773705
      },
      {
        "latitude": 8.83092,
        "longitude": -78.768555
      },
      {
        "latitude": 8.825323333333333,
        "longitude": -78.77954166666666
      },
      {
        "latitude": 8.822778333333334,
        "longitude": -78.77336166666667
      },
      {
        "latitude": 8.819555,
        "longitude": -78.76495
      },
      {
        "latitude": 8.81294,
        "longitude": -78.75671
      },
      {
        "latitude": 8.812261666666666,
        "longitude": -78.75173166666667
      },
      {
        "latitude": 8.801235,
        "longitude": -78.75053
      },
      {
        "latitude": 8.801913333333333,
        "longitude": -78.75585166666667
      },
      {
        "latitude": 8.787153333333332,
        "longitude": -78.75259
      },
      {
        "latitude": 8.783251666666667,
        "longitude": -78.75173166666667
      },
      {
        "latitude": 8.781216666666667,
        "longitude": -78.751045
      },
      {
        "latitude": 8.778501666666667,
        "longitude": -78.753105
      },
      {
        "latitude": 8.777145,
        "longitude": -78.75018666666666
      },
      {
        "latitude": 8.776466666666666,
        "longitude": -78.74452166666667
      },
      {
        "latitude": 8.771206666666666,
        "longitude": -78.74229
      },
      {
        "latitude": 8.771036666666667,
        "longitude": -78.73937166666667
      },
      {
        "latitude": 8.766456666666667,
        "longitude": -78.73954333333333
      },
      {
        "latitude": 8.765778333333333,
        "longitude": -78.73508166666667
      },
      {
        "latitude": 8.762893333333333,
        "longitude": -78.72958833333334
      },
      {
        "latitude": 8.758991666666667,
        "longitude": -78.719975
      },
      {
        "latitude": 8.758313333333334,
        "longitude": -78.71345166666667
      },
      {
        "latitude": 8.760858333333333,
        "longitude": -78.71396666666666
      },
      {
        "latitude": 8.76442,
        "longitude": -78.71825833333334
      },
      {
        "latitude": 8.766965,
        "longitude": -78.72083333333333
      },
      {
        "latitude": 8.76968,
        "longitude": -78.72134833333334
      },
      {
        "latitude": 8.77002,
        "longitude": -78.71808666666666
      },
      {
        "latitude": 8.765948333333334,
        "longitude": -78.71396666666666
      },
      {
        "latitude": 8.761196666666667,
        "longitude": -78.71019
      },
      {
        "latitude": 8.759161666666667,
        "longitude": -78.70881666666666
      },
      {
        "latitude": 8.760518333333334,
        "longitude": -78.70504
      },
      {
        "latitude": 8.758313333333334,
        "longitude": -78.70195
      },
      {
        "latitude": 8.753901666666666,
        "longitude": -78.70177833333334
      },
      {
        "latitude": 8.752205,
        "longitude": -78.70332333333333
      },
      {
        "latitude": 8.751018333333333,
        "longitude": -78.69954666666666
      },
      {
        "latitude": 8.751018333333333,
        "longitude": -78.694225
      },
      {
        "latitude": 8.749321666666667,
        "longitude": -78.69079166666667
      },
      {
        "latitude": 8.751018333333333,
        "longitude": -78.68667166666667
      },
      {
        "latitude": 8.756106666666666,
        "longitude": -78.68461166666667
      },
      {
        "latitude": 8.76018,
        "longitude": -78.68049333333333
      },
      {
        "latitude": 8.75475,
        "longitude": -78.68083666666666
      },
      {
        "latitude": 8.749321666666667,
        "longitude": -78.67809
      },
      {
        "latitude": 8.74949,
        "longitude": -78.67397
      },
      {
        "latitude": 8.746776666666667,
        "longitude": -78.67431333333333
      },
      {
        "latitude": 8.743468333333333,
        "longitude": -78.67148
      },
      {
        "latitude": 8.739735,
        "longitude": -78.67010666666667
      },
      {
        "latitude": 8.733966666666667,
        "longitude": -78.67010666666667
      },
      {
        "latitude": 8.722768333333333,
        "longitude": -78.67079333333334
      },
      {
        "latitude": 8.720391666666666,
        "longitude": -78.66598666666667
      },
      {
        "latitude": 8.734645,
        "longitude": -78.65500166666666
      },
      {
        "latitude": 8.737698333333332,
        "longitude": -78.64538833333333
      },
      {
        "latitude": 8.732608333333333,
        "longitude": -78.63337166666666
      },
      {
        "latitude": 8.72175,
        "longitude": -78.624445
      },
      {
        "latitude": 8.712926666666666,
        "longitude": -78.63234166666666
      },
      {
        "latitude": 8.700708333333333,
        "longitude": -78.63234166666666
      },
      {
        "latitude": 8.693581666666667,
        "longitude": -78.62169833333333
      },
      {
        "latitude": 8.685436666666666,
        "longitude": -78.61963833333333
      },
      {
        "latitude": 8.689848333333334,
        "longitude": -78.60624833333333
      },
      {
        "latitude": 8.692225,
        "longitude": -78.59835333333334
      },
      {
        "latitude": 8.708853333333334,
        "longitude": -78.60418833333334
      },
      {
        "latitude": 8.71123,
        "longitude": -78.59629333333334
      },
      {
        "latitude": 8.702406666666667,
        "longitude": -78.59183
      },
      {
        "latitude": 8.693581666666667,
        "longitude": -78.58874
      },
      {
        "latitude": 8.688831666666667,
        "longitude": -78.59114333333333
      },
      {
        "latitude": 8.675255,
        "longitude": -78.57775333333333
      },
      {
        "latitude": 8.668128333333334,
        "longitude": -78.57569333333333
      },
      {
        "latitude": 8.659643333333333,
        "longitude": -78.56333333333333
      },
      {
        "latitude": 8.651158333333333,
        "longitude": -78.54994333333333
      },
      {
        "latitude": 8.650478333333334,
        "longitude": -78.539645
      },
      {
        "latitude": 8.647763333333334,
        "longitude": -78.52865833333334
      },
      {
        "latitude": 8.644368333333333,
        "longitude": -78.518015
      },
      {
        "latitude": 8.634865,
        "longitude": -78.51320833333334
      },
      {
        "latitude": 8.63215,
        "longitude": -78.518015
      },
      {
        "latitude": 8.618911666666667,
        "longitude": -78.51320833333334
      },
      {
        "latitude": 8.610086666666668,
        "longitude": -78.50737166666667
      },
      {
        "latitude": 8.603296666666667,
        "longitude": -78.51149166666667
      },
      {
        "latitude": 8.600581666666667,
        "longitude": -78.50187833333334
      },
      {
        "latitude": 8.596168333333333,
        "longitude": -78.49467
      },
      {
        "latitude": 8.5887,
        "longitude": -78.50290833333334
      },
      {
        "latitude": 8.580551666666667,
        "longitude": -78.49398333333333
      },
      {
        "latitude": 8.566633333333334,
        "longitude": -78.48952
      },
      {
        "latitude": 8.558825,
        "longitude": -78.48952
      },
      {
        "latitude": 8.544226666666667,
        "longitude": -78.48780333333333
      },
      {
        "latitude": 8.551016666666667,
        "longitude": -78.50222166666667
      },
      {
        "latitude": 8.559843333333333,
        "longitude": -78.51320833333334
      },
      {
        "latitude": 8.569688333333334,
        "longitude": -78.522135
      },
      {
        "latitude": 8.578515,
        "longitude": -78.52247833333334
      },
      {
        "latitude": 8.58191,
        "longitude": -78.53003166666667
      },
      {
        "latitude": 8.56256,
        "longitude": -78.52453833333334
      },
      {
        "latitude": 8.553393333333334,
        "longitude": -78.51835833333334
      },
      {
        "latitude": 8.543546666666666,
        "longitude": -78.505655
      },
      {
        "latitude": 8.53438,
        "longitude": -78.50084833333334
      },
      {
        "latitude": 8.533021666666667,
        "longitude": -78.50840166666667
      },
      {
        "latitude": 8.528608333333333,
        "longitude": -78.50222166666667
      },
      {
        "latitude": 8.525213333333333,
        "longitude": -78.49810166666667
      },
      {
        "latitude": 8.518761666666666,
        "longitude": -78.49398333333333
      },
      {
        "latitude": 8.510273333333334,
        "longitude": -78.49295333333333
      },
      {
        "latitude": 8.502125,
        "longitude": -78.48608666666667
      },
      {
        "latitude": 8.498728333333334,
        "longitude": -78.49020666666667
      },
      {
        "latitude": 8.503821666666667,
        "longitude": -78.49878833333334
      },
      {
        "latitude": 8.495333333333333,
        "longitude": -78.50016166666667
      },
      {
        "latitude": 8.480731666666667,
        "longitude": -78.49707166666667
      },
      {
        "latitude": 8.469865,
        "longitude": -78.49775833333334
      },
      {
        "latitude": 8.470545,
        "longitude": -78.50531166666667
      },
      {
        "latitude": 8.458998333333334,
        "longitude": -78.499475
      },
      {
        "latitude": 8.44949,
        "longitude": -78.49261
      },
      {
        "latitude": 8.439981666666666,
        "longitude": -78.47922
      },
      {
        "latitude": 8.447453333333334,
        "longitude": -78.47613
      },
      {
        "latitude": 8.454585,
        "longitude": -78.47338333333333
      },
      {
        "latitude": 8.463753333333333,
        "longitude": -78.46583
      },
      {
        "latitude": 8.460018333333334,
        "longitude": -78.45999333333333
      },
      {
        "latitude": 8.453226666666666,
        "longitude": -78.45965
      },
      {
        "latitude": 8.446095,
        "longitude": -78.45484333333333
      },
      {
        "latitude": 8.437943333333333,
        "longitude": -78.44935
      },
      {
        "latitude": 8.43285,
        "longitude": -78.44900666666666
      },
      {
        "latitude": 8.429453333333333,
        "longitude": -78.45621666666666
      },
      {
        "latitude": 8.42402,
        "longitude": -78.45415666666666
      },
      {
        "latitude": 8.417566666666666,
        "longitude": -78.44557333333333
      },
      {
        "latitude": 8.388358333333333,
        "longitude": -78.44660333333333
      },
      {
        "latitude": 8.391755,
        "longitude": -78.43905166666667
      },
      {
        "latitude": 8.378168333333333,
        "longitude": -78.43458833333334
      },
      {
        "latitude": 8.35711,
        "longitude": -78.42016833333334
      },
      {
        "latitude": 8.352353333333333,
        "longitude": -78.41639166666667
      },
      {
        "latitude": 7.925567,
        "longitude": -78.747883
      },
      {
        "latitude": 7.952433,
        "longitude": -79.1748
      },
      {
        "latitude": 8.084,
        "longitude": -79.342333
      },
      {
        "latitude": 8.348367,
        "longitude": -79.3389
      },
      {
        "latitude": 8.38778333,
        "longitude": -79.45215
      }
    ]
  }